[
  {
    "id": 1,
    "Name_pt": "Abacate",
    "Cod_Fresco": 34,
    "Cod_Mix": 409,
    "Categoria_Alimentos": "Frutas",
    "Inicial_Nome": "A"
  },
  {
    "id": 2,
    "Name_pt": "Abacaxi havai",
    "Cod_Fresco": 7,
    "Cod_Mix": 417,
    "Categoria_Alimentos": "Frutas",
    "Inicial_Nome": "A"
  },
  {
    "id": 3,
    "Name_pt": "Abacaxi perola",
    "Cod_Fresco": 9955,
    "Cod_Mix": 418,
    "Categoria_Alimentos": "Frutas",
    "Inicial_Nome": "A"
  },
  {
    "id": 6,
    "Name_pt": "Abóbora cabotiá",
    "Cod_Fresco": 9796,
    "Cod_Mix": 375,
    "Categoria_Alimentos": "Hortaliças",
    "Inicial_Nome": "A"
  },
  {
    "id": 5,
    "Name_pt": "Abóbora menina",
    "Cod_Fresco": 9819,
    "Cod_Mix": 378,
    "Categoria_Alimentos": "Hortaliças",
    "Inicial_Nome": "A"
  },
  {
    "id": 7,
    "Name_pt": "Abóbora moranga",
    "Cod_Fresco": 2563,
    "Cod_Mix": 379,
    "Categoria_Alimentos": "Hortaliças",
    "Inicial_Nome": "A"
  },
  {
    "id": 8,
    "Name_pt": "Abóbora pescoço",
    "Cod_Fresco": 2565,
    "Cod_Mix": 380,
    "Categoria_Alimentos": "Hortaliças",
    "Inicial_Nome": "A"
  },
  {
    "id": 9,
    "Name_pt": "Abobrinha italiana",
    "Cod_Fresco": 32,
    "Cod_Mix": 362,
    "Categoria_Alimentos": "Hortaliças",
    "Inicial_Nome": "A"
  },
  {
    "id": 4,
    "Name_pt": "Acelga",
    "Cod_Fresco": 29,
    "Cod_Mix": null,
    "Categoria_Alimentos": "Hortaliças",
    "Inicial_Nome": "A"
  },
  {
    "id": 22,
    "Name_pt": "Agrião comum",
    "Cod_Fresco": 42,
    "Cod_Mix": null,
    "Categoria_Alimentos": "Hortaliças",
    "Inicial_Nome": "A"
  },
  {
    "id": 21,
    "Name_pt": "Agrião hidroponico",
    "Cod_Fresco": 6008,
    "Cod_Mix": null,
    "Categoria_Alimentos": "Hortaliças",
    "Inicial_Nome": "A"
  },
  {
    "id": 12,
    "Name_pt": "Alface americana",
    "Cod_Fresco": 52,
    "Cod_Mix": null,
    "Categoria_Alimentos": "Hortaliças",
    "Inicial_Nome": "A"
  },
  {
    "id": 16,
    "Name_pt": "Alface coração",
    "Cod_Fresco": 1989,
    "Cod_Mix": null,
    "Categoria_Alimentos": "Hortaliças",
    "Inicial_Nome": "A"
  },
  {
    "id": 13,
    "Name_pt": "Alface crespa",
    "Cod_Fresco": 30,
    "Cod_Mix": null,
    "Categoria_Alimentos": "Hortaliças",
    "Inicial_Nome": "A"
  },
  {
    "id": 17,
    "Name_pt": "Alface crespa hidropônica",
    "Cod_Fresco": 4564,
    "Cod_Mix": null,
    "Categoria_Alimentos": "Hortaliças",
    "Inicial_Nome": "A"
  },
  {
    "id": 15,
    "Name_pt": "Alface frisée",
    "Cod_Fresco": 3342,
    "Cod_Mix": null,
    "Categoria_Alimentos": "Hortaliças",
    "Inicial_Nome": "A"
  },
  {
    "id": 18,
    "Name_pt": "Alface lisa",
    "Cod_Fresco": 44,
    "Cod_Mix": null,
    "Categoria_Alimentos": "Hortaliças",
    "Inicial_Nome": "A"
  },
  {
    "id": 14,
    "Name_pt": "Alface roxa",
    "Cod_Fresco": 9897,
    "Cod_Mix": null,
    "Categoria_Alimentos": "Hortaliças",
    "Inicial_Nome": "A"
  },
  {
    "id": 19,
    "Name_pt": "Alho",
    "Cod_Fresco": 1224,
    "Cod_Mix": 352,
    "Categoria_Alimentos": "Hortaliças",
    "Inicial_Nome": "A"
  },
  {
    "id": 20,
    "Name_pt": "Alho-poró",
    "Cod_Fresco": 3310,
    "Cod_Mix": null,
    "Categoria_Alimentos": "Hortaliças",
    "Inicial_Nome": "A"
  },
  {
    "id": 23,
    "Name_pt": "Almeirão",
    "Cod_Fresco": 3031,
    "Cod_Mix": null,
    "Categoria_Alimentos": "Hortaliças",
    "Inicial_Nome": "A"
  },
  {
    "id": 10,
    "Name_pt": "Ameixa",
    "Cod_Fresco": 13,
    "Cod_Mix": 414,
    "Categoria_Alimentos": "Frutas",
    "Inicial_Nome": "A"
  },
  {
    "id": 11,
    "Name_pt": "Atemoia",
    "Cod_Fresco": 9794,
    "Cod_Mix": 429,
    "Categoria_Alimentos": "Frutas",
    "Inicial_Nome": "A"
  },
  {
    "id": 24,
    "Name_pt": "Banana caturra",
    "Cod_Fresco": 35,
    "Cod_Mix": 522,
    "Categoria_Alimentos": "Frutas",
    "Inicial_Nome": "B"
  },
  {
    "id": 28,
    "Name_pt": "Banana da terra",
    "Cod_Fresco": 853,
    "Cod_Mix": 395,
    "Categoria_Alimentos": "Frutas",
    "Inicial_Nome": "B"
  },
  {
    "id": 26,
    "Name_pt": "Banana maçã",
    "Cod_Fresco": 69,
    "Cod_Mix": 396,
    "Categoria_Alimentos": "Frutas",
    "Inicial_Nome": "B"
  },
  {
    "id": 27,
    "Name_pt": "Banana madura",
    "Cod_Fresco": 1652,
    "Cod_Mix": null,
    "Categoria_Alimentos": "Frutas",
    "Inicial_Nome": "B"
  },
  {
    "id": 25,
    "Name_pt": "Banana prata",
    "Cod_Fresco": 51,
    "Cod_Mix": null,
    "Categoria_Alimentos": "Frutas",
    "Inicial_Nome": "B"
  },
  {
    "id": 33,
    "Name_pt": "Batata 3kg",
    "Cod_Fresco": 492,
    "Cod_Mix": null,
    "Categoria_Alimentos": "Tubérculos",
    "Inicial_Nome": "B"
  },
  {
    "id": 32,
    "Name_pt": "Batata 5kg",
    "Cod_Fresco": 59,
    "Cod_Mix": null,
    "Categoria_Alimentos": "Tubérculos",
    "Inicial_Nome": "B"
  },
  {
    "id": 30,
    "Name_pt": "Batata asterix",
    "Cod_Fresco": 96162,
    "Cod_Mix": 383,
    "Categoria_Alimentos": "Tubérculos",
    "Inicial_Nome": "B"
  },
  {
    "id": 29,
    "Name_pt": "Batata bolinha",
    "Cod_Fresco": 2018,
    "Cod_Mix": 746,
    "Categoria_Alimentos": "Tubérculos",
    "Inicial_Nome": "B"
  },
  {
    "id": 35,
    "Name_pt": "Batata-doce",
    "Cod_Fresco": 28,
    "Cod_Mix": 509,
    "Categoria_Alimentos": "Tubérculos",
    "Inicial_Nome": "B"
  },
  {
    "id": 36,
    "Name_pt": "Batata-doce roxa",
    "Cod_Fresco": 6443,
    "Cod_Mix": 382,
    "Categoria_Alimentos": "Tubérculos",
    "Inicial_Nome": "B"
  },
  {
    "id": 31,
    "Name_pt": "Batata monalisa",
    "Cod_Fresco": 20,
    "Cod_Mix": 360,
    "Categoria_Alimentos": "Tubérculos",
    "Inicial_Nome": "B"
  },
  {
    "id": 34,
    "Name_pt": "Batata salsa",
    "Cod_Fresco": 31,
    "Cod_Mix": 372,
    "Categoria_Alimentos": "Tubérculos",
    "Inicial_Nome": "B"
  },
  {
    "id": 41,
    "Name_pt": "Berinjela",
    "Cod_Fresco": 66,
    "Cod_Mix": 361,
    "Categoria_Alimentos": "Hortaliças",
    "Inicial_Nome": "B"
  },
  {
    "id": 37,
    "Name_pt": "Beterraba",
    "Cod_Fresco": 2727,
    "Cod_Mix": 983,
    "Categoria_Alimentos": "Hortaliças",
    "Inicial_Nome": "B"
  },
  {
    "id": 38,
    "Name_pt": "Beterraba mç",
    "Cod_Fresco": 27,
    "Cod_Mix": 491,
    "Categoria_Alimentos": "Hortaliças",
    "Inicial_Nome": "B"
  },
  {
    "id": 39,
    "Name_pt": "Brócolis",
    "Cod_Fresco": 50,
    "Cod_Mix": 373,
    "Categoria_Alimentos": "Hortaliças",
    "Inicial_Nome": "B"
  },
  {
    "id": 40,
    "Name_pt": "Broto de alfafa",
    "Cod_Fresco": 4036,
    "Cod_Mix": null,
    "Categoria_Alimentos": "Hortaliças",
    "Inicial_Nome": "B"
  },
  {
    "id": 43,
    "Name_pt": "Caqui",
    "Cod_Fresco": 2595,
    "Cod_Mix": 415,
    "Categoria_Alimentos": "Frutas",
    "Inicial_Nome": "C"
  },
  {
    "id": 44,
    "Name_pt": "Carambola",
    "Cod_Fresco": 2448,
    "Cod_Mix": 391,
    "Categoria_Alimentos": "Frutas",
    "Inicial_Nome": "C"
  },
  {
    "id": 45,
    "Name_pt": "Cebola branca",
    "Cod_Fresco": 19,
    "Cod_Mix": 366,
    "Categoria_Alimentos": "Hortaliças",
    "Inicial_Nome": "C"
  },
  {
    "id": 47,
    "Name_pt": "Cebola conserva",
    "Cod_Fresco": 1827,
    "Cod_Mix": 368,
    "Categoria_Alimentos": "Hortaliças",
    "Inicial_Nome": "C"
  },
  {
    "id": 46,
    "Name_pt": "Cebola roxa",
    "Cod_Fresco": 48,
    "Cod_Mix": 367,
    "Categoria_Alimentos": "Hortaliças",
    "Inicial_Nome": "C"
  },
  {
    "id": 48,
    "Name_pt": "Cenoura comum",
    "Cod_Fresco": 25,
    "Cod_Mix": 363,
    "Categoria_Alimentos": "Hortaliças",
    "Inicial_Nome": "C"
  },
  {
    "id": 42,
    "Name_pt": "Cereja",
    "Cod_Fresco": 886,
    "Cod_Mix": null,
    "Categoria_Alimentos": "Frutas",
    "Inicial_Nome": "C"
  },
  {
    "id": 55,
    "Name_pt": "Cheiro verde",
    "Cod_Fresco": 26,
    "Cod_Mix": null,
    "Categoria_Alimentos": "Hortaliças",
    "Inicial_Nome": "C"
  },
  {
    "id": 49,
    "Name_pt": "Chuchu",
    "Cod_Fresco": 36,
    "Cod_Mix": 381,
    "Categoria_Alimentos": "Hortaliças",
    "Inicial_Nome": "C"
  },
  {
    "id": 53,
    "Name_pt": "Coco",
    "Cod_Fresco": 11,
    "Cod_Mix": 553,
    "Categoria_Alimentos": "Frutas",
    "Inicial_Nome": "C"
  },
  {
    "id": 54,
    "Name_pt": "Coco verde",
    "Cod_Fresco": 20181,
    "Cod_Mix": 657,
    "Categoria_Alimentos": "Frutas",
    "Inicial_Nome": "C"
  },
  {
    "id": 52,
    "Name_pt": "Coentro",
    "Cod_Fresco": 230,
    "Cod_Mix": null,
    "Categoria_Alimentos": "Hortaliças",
    "Inicial_Nome": "C"
  },
  {
    "id": 57,
    "Name_pt": "Cogumelo champignon",
    "Cod_Fresco": 5313,
    "Cod_Mix": 493,
    "Categoria_Alimentos": "Hortaliças",
    "Inicial_Nome": "C"
  },
  {
    "id": 58,
    "Name_pt": "Cogumelo shimeji",
    "Cod_Fresco": 564,
    "Cod_Mix": null,
    "Categoria_Alimentos": "Hortaliças",
    "Inicial_Nome": "C"
  },
  {
    "id": 59,
    "Name_pt": "Cogumelo shitake",
    "Cod_Fresco": 788,
    "Cod_Mix": null,
    "Categoria_Alimentos": "Hortaliças",
    "Inicial_Nome": "C"
  },
  {
    "id": 50,
    "Name_pt": "Couve-flor",
    "Cod_Fresco": 24,
    "Cod_Mix": 374,
    "Categoria_Alimentos": "Hortaliças",
    "Inicial_Nome": "C"
  },
  {
    "id": 56,
    "Name_pt": "Couve-flor orgânica",
    "Cod_Fresco": 3017,
    "Cod_Mix": null,
    "Categoria_Alimentos": "Hortaliças",
    "Inicial_Nome": "C"
  },
  {
    "id": 51,
    "Name_pt": "Couve manteiga",
    "Cod_Fresco": 54,
    "Cod_Mix": 747,
    "Categoria_Alimentos": "Hortaliças",
    "Inicial_Nome": "C"
  },
  {
    "id": 60,
    "Name_pt": "Ervilha",
    "Cod_Fresco": 4951,
    "Cod_Mix": 433,
    "Categoria_Alimentos": "Hortaliças",
    "Inicial_Nome": "E"
  },
  {
    "id": 61,
    "Name_pt": "Escarola",
    "Cod_Fresco": 65,
    "Cod_Mix": null,
    "Categoria_Alimentos": "Hortaliças",
    "Inicial_Nome": "E"
  },
  {
    "id": 62,
    "Name_pt": "Espinafre",
    "Cod_Fresco": 2985,
    "Cod_Mix": null,
    "Categoria_Alimentos": "Hortaliças",
    "Inicial_Nome": "E"
  },
  {
    "id": 67,
    "Name_pt": "Figo roxo",
    "Cod_Fresco": 6363,
    "Cod_Mix": null,
    "Categoria_Alimentos": "Frutas",
    "Inicial_Nome": "F"
  },
  {
    "id": 65,
    "Name_pt": "Gengibre",
    "Cod_Fresco": 1888,
    "Cod_Mix": 351,
    "Categoria_Alimentos": "Hortaliças",
    "Inicial_Nome": "G"
  },
  {
    "id": 63,
    "Name_pt": "Goiaba",
    "Cod_Fresco": 14,
    "Cod_Mix": 419,
    "Categoria_Alimentos": "Frutas",
    "Inicial_Nome": "G"
  },
  {
    "id": 64,
    "Name_pt": "Hortelã",
    "Cod_Fresco": 6405,
    "Cod_Mix": null,
    "Categoria_Alimentos": "Hortaliças",
    "Inicial_Nome": "H"
  },
  {
    "id": 66,
    "Name_pt": "Inhame",
    "Cod_Fresco": 9797,
    "Cod_Mix": 371,
    "Categoria_Alimentos": "Tubérculos",
    "Inicial_Nome": "I"
  },
  {
    "id": 69,
    "Name_pt": "Jabuticaba",
    "Cod_Fresco": 537,
    "Cod_Mix": 1280,
    "Categoria_Alimentos": "Frutas",
    "Inicial_Nome": "J"
  },
  {
    "id": 68,
    "Name_pt": "Jiló",
    "Cod_Fresco": 1657,
    "Cod_Mix": 489,
    "Categoria_Alimentos": "Hortaliças",
    "Inicial_Nome": "J"
  },
  {
    "id": 70,
    "Name_pt": "Kiwi",
    "Cod_Fresco": 45,
    "Cod_Mix": 403,
    "Categoria_Alimentos": "Frutas",
    "Inicial_Nome": "K"
  },
  {
    "id": 71,
    "Name_pt": "Laranja Bahia",
    "Cod_Fresco": 2644,
    "Cod_Mix": 404,
    "Categoria_Alimentos": "Frutas",
    "Inicial_Nome": "L"
  },
  {
    "id": 72,
    "Name_pt": "Laranja Lima",
    "Cod_Fresco": 9,
    "Cod_Mix": 405,
    "Categoria_Alimentos": "Frutas",
    "Inicial_Nome": "L"
  },
  {
    "id": 73,
    "Name_pt": "Laranja Pera",
    "Cod_Fresco": 1999,
    "Cod_Mix": 406,
    "Categoria_Alimentos": "Frutas",
    "Inicial_Nome": "L"
  },
  {
    "id": 74,
    "Name_pt": "Limão",
    "Cod_Fresco": 10,
    "Cod_Mix": 411,
    "Categoria_Alimentos": "Frutas",
    "Inicial_Nome": "L"
  },
  {
    "id": 75,
    "Name_pt": "Limão siciliano",
    "Cod_Fresco": 398,
    "Cod_Mix": 961,
    "Categoria_Alimentos": "Frutas",
    "Inicial_Nome": "L"
  },
  {
    "id": 76,
    "Name_pt": "Maçã argentina",
    "Cod_Fresco": 2,
    "Cod_Mix": 398,
    "Categoria_Alimentos": "Frutas",
    "Inicial_Nome": "M"
  },
  {
    "id": 77,
    "Name_pt": "Maçã Fuji",
    "Cod_Fresco": 289,
    "Cod_Mix": 397,
    "Categoria_Alimentos": "Frutas",
    "Inicial_Nome": "M"
  },
  {
    "id": 78,
    "Name_pt": "Maçã Gala",
    "Cod_Fresco": 3,
    "Cod_Mix": 399,
    "Categoria_Alimentos": "Frutas",
    "Inicial_Nome": "M"
  },
  {
    "id": 79,
    "Name_pt": "Maçã Pink Lady",
    "Cod_Fresco": 4409,
    "Cod_Mix": 400,
    "Categoria_Alimentos": "Frutas",
    "Inicial_Nome": "M"
  },
  {
    "id": 80,
    "Name_pt": "Maçã verde",
    "Cod_Fresco": 616,
    "Cod_Mix": 401,
    "Categoria_Alimentos": "Frutas",
    "Inicial_Nome": "M"
  },
  {
    "id": 81,
    "Name_pt": "Mamão Formosa",
    "Cod_Fresco": 5,
    "Cod_Mix": 384,
    "Categoria_Alimentos": "Frutas",
    "Inicial_Nome": "M"
  },
  {
    "id": 82,
    "Name_pt": "Mamão Papaia",
    "Cod_Fresco": 6,
    "Cod_Mix": 385,
    "Categoria_Alimentos": "Frutas",
    "Inicial_Nome": "M"
  },
  {
    "id": 84,
    "Name_pt": "Mandioca",
    "Cod_Fresco": 33,
    "Cod_Mix": 370,
    "Categoria_Alimentos": "Tubérculos",
    "Inicial_Nome": "M"
  },
  {
    "id": 83,
    "Name_pt": "Mandioca embalada",
    "Cod_Fresco": 40,
    "Cod_Mix": 520,
    "Categoria_Alimentos": "Tubérculos",
    "Inicial_Nome": "M"
  },
  {
    "id": 85,
    "Name_pt": "Manga espada",
    "Cod_Fresco": 1544,
    "Cod_Mix": 387,
    "Categoria_Alimentos": "Frutas",
    "Inicial_Nome": "M"
  },
  {
    "id": 86,
    "Name_pt": "Manga Palmer",
    "Cod_Fresco": 1562,
    "Cod_Mix": 388,
    "Categoria_Alimentos": "Frutas",
    "Inicial_Nome": "M"
  },
  {
    "id": 87,
    "Name_pt": "Manga Tommy",
    "Cod_Fresco": 4,
    "Cod_Mix": 389,
    "Categoria_Alimentos": "Frutas",
    "Inicial_Nome": "M"
  },
  {
    "id": 88,
    "Name_pt": "Manjericão",
    "Cod_Fresco": 6367,
    "Cod_Mix": null,
    "Categoria_Alimentos": "Hortaliças",
    "Inicial_Nome": "M"
  },
  {
    "id": 89,
    "Name_pt": "Maracujá",
    "Cod_Fresco": 12,
    "Cod_Mix": 386,
    "Categoria_Alimentos": "Frutas",
    "Inicial_Nome": "M"
  },
  {
    "id": 91,
    "Name_pt": "Melancia",
    "Cod_Fresco": 15,
    "Cod_Mix": null,
    "Categoria_Alimentos": "Frutas",
    "Inicial_Nome": "M"
  },
  {
    "id": 90,
    "Name_pt": "Melancia baby",
    "Cod_Fresco": 1758,
    "Cod_Mix": null,
    "Categoria_Alimentos": "Frutas",
    "Inicial_Nome": "M"
  },
  {
    "id": 92,
    "Name_pt": "Melão",
    "Cod_Fresco": 53,
    "Cod_Mix": 393,
    "Categoria_Alimentos": "Frutas",
    "Inicial_Nome": "M"
  },
  {
    "id": 93,
    "Name_pt": "Mexerica",
    "Cod_Fresco": 1829,
    "Cod_Mix": 766,
    "Categoria_Alimentos": "Frutas",
    "Inicial_Nome": "M"
  },
  {
    "id": 94,
    "Name_pt": "Milho verde bdj",
    "Cod_Fresco": 989898,
    "Cod_Mix": 477,
    "Categoria_Alimentos": "Hortaliças",
    "Inicial_Nome": "M"
  },
  {
    "id": 95,
    "Name_pt": "Milho verde uni",
    "Cod_Fresco": 97884,
    "Cod_Mix": null,
    "Categoria_Alimentos": "Hortaliças",
    "Inicial_Nome": "M"
  },
  {
    "id": 96,
    "Name_pt": "Morango bandeja",
    "Cod_Fresco": 710,
    "Cod_Mix": 407,
    "Categoria_Alimentos": "Frutas",
    "Inicial_Nome": "M"
  },
  {
    "id": 97,
    "Name_pt": "Morango kg",
    "Cod_Fresco": 1515,
    "Cod_Mix": null,
    "Categoria_Alimentos": "Frutas",
    "Inicial_Nome": "M"
  },
  {
    "id": 98,
    "Name_pt": "Morgote",
    "Cod_Fresco": 3207,
    "Cod_Mix": 413,
    "Categoria_Alimentos": "Frutas",
    "Inicial_Nome": "M"
  },
  {
    "id": 99,
    "Name_pt": "Nabo",
    "Cod_Fresco": 1900,
    "Cod_Mix": null,
    "Categoria_Alimentos": "Hortaliças",
    "Inicial_Nome": "N"
  },
  {
    "id": 100,
    "Name_pt": "Nectarina",
    "Cod_Fresco": 97856,
    "Cod_Mix": 518,
    "Categoria_Alimentos": "Frutas",
    "Inicial_Nome": "N"
  },
  {
    "id": 101,
    "Name_pt": "Ovos branco c/12",
    "Cod_Fresco": 47,
    "Cod_Mix": null,
    "Categoria_Alimentos": "Proteínas",
    "Inicial_Nome": "O"
  },
  {
    "id": 102,
    "Name_pt": "Ovos branco c/30",
    "Cod_Fresco": 204,
    "Cod_Mix": null,
    "Categoria_Alimentos": "Proteínas",
    "Inicial_Nome": "O"
  },
  {
    "id": 103,
    "Name_pt": "Ovos caipira",
    "Cod_Fresco": 1832,
    "Cod_Mix": null,
    "Categoria_Alimentos": "Proteínas",
    "Inicial_Nome": "O"
  },
  {
    "id": 104,
    "Name_pt": "Ovos codorna",
    "Cod_Fresco": 1625,
    "Cod_Mix": null,
    "Categoria_Alimentos": "Proteínas",
    "Inicial_Nome": "O"
  },
  {
    "id": 105,
    "Name_pt": "Ovos vermelho c/30",
    "Cod_Fresco": 1632,
    "Cod_Mix": null,
    "Categoria_Alimentos": "Proteínas",
    "Inicial_Nome": "O"
  },
  {
    "id": 106,
    "Name_pt": "Ovos vermelhos c/12",
    "Cod_Fresco": 16,
    "Cod_Mix": null,
    "Categoria_Alimentos": "Proteínas",
    "Inicial_Nome": "O"
  },
  {
    "id": 107,
    "Name_pt": "Pepino conserva",
    "Cod_Fresco": 9953,
    "Cod_Mix": null,
    "Categoria_Alimentos": "Hortaliças",
    "Inicial_Nome": "P"
  },
  {
    "id": 108,
    "Name_pt": "Pepino japonês",
    "Cod_Fresco": 2415,
    "Cod_Mix": 365,
    "Categoria_Alimentos": "Hortaliças",
    "Inicial_Nome": "P"
  },
  {
    "id": 109,
    "Name_pt": "Pepino salada",
    "Cod_Fresco": 21,
    "Cod_Mix": 364,
    "Categoria_Alimentos": "Hortaliças",
    "Inicial_Nome": "P"
  },
  {
    "id": 110,
    "Name_pt": "Pera Williams",
    "Cod_Fresco": 43,
    "Cod_Mix": 431,
    "Categoria_Alimentos": "Frutas",
    "Inicial_Nome": "P"
  },
  {
    "id": 111,
    "Name_pt": "Pêssego amarelo",
    "Cod_Fresco": 901,
    "Cod_Mix": 634,
    "Categoria_Alimentos": "Frutas",
    "Inicial_Nome": "P"
  },
  {
    "id": 112,
    "Name_pt": "Pêssego branco",
    "Cod_Fresco": 900,
    "Cod_Mix": 488,
    "Categoria_Alimentos": "Frutas",
    "Inicial_Nome": "P"
  },
  {
    "id": 113,
    "Name_pt": "Pimenta cambuci bdj",
    "Cod_Fresco": 1830,
    "Cod_Mix": null,
    "Categoria_Alimentos": "Hortaliças",
    "Inicial_Nome": "P"
  },
  {
    "id": 114,
    "Name_pt": "Pimenta cambuci kg",
    "Cod_Fresco": 9848,
    "Cod_Mix": 639,
    "Categoria_Alimentos": "Hortaliças",
    "Inicial_Nome": "P"
  },
  {
    "id": 115,
    "Name_pt": "Pimenta dedo de moça bdj",
    "Cod_Fresco": 89,
    "Cod_Mix": 434,
    "Categoria_Alimentos": "Hortaliças",
    "Inicial_Nome": "P"
  },
  {
    "id": 116,
    "Name_pt": "Pimentão amarelo",
    "Cod_Fresco": 301,
    "Cod_Mix": 357,
    "Categoria_Alimentos": "Hortaliças",
    "Inicial_Nome": "P"
  },
  {
    "id": 117,
    "Name_pt": "Pimentão verde",
    "Cod_Fresco": 22,
    "Cod_Mix": 359,
    "Categoria_Alimentos": "Hortaliças",
    "Inicial_Nome": "P"
  },
  {
    "id": 118,
    "Name_pt": "Pimentão vermelho",
    "Cod_Fresco": 300,
    "Cod_Mix": 358,
    "Categoria_Alimentos": "Hortaliças",
    "Inicial_Nome": "P"
  },
  {
    "id": 119,
    "Name_pt": "Pinhão",
    "Cod_Fresco": 9795,
    "Cod_Mix": 718,
    "Categoria_Alimentos": "Frutas",
    "Inicial_Nome": "P"
  },
  {
    "id": 120,
    "Name_pt": "Pitaya",
    "Cod_Fresco": 78,
    "Cod_Mix": 428,
    "Categoria_Alimentos": "Frutas",
    "Inicial_Nome": "P"
  },
  {
    "id": 121,
    "Name_pt": "Quiabo",
    "Cod_Fresco": 1831,
    "Cod_Mix": 992,
    "Categoria_Alimentos": "Hortaliças",
    "Inicial_Nome": "Q"
  },
  {
    "id": 122,
    "Name_pt": "Rabanete",
    "Cod_Fresco": 67,
    "Cod_Mix": 432,
    "Categoria_Alimentos": "Hortaliças",
    "Inicial_Nome": "R"
  },
  {
    "id": 123,
    "Name_pt": "Radicchio roxo",
    "Cod_Fresco": 6368,
    "Cod_Mix": null,
    "Categoria_Alimentos": "Hortaliças",
    "Inicial_Nome": "R"
  },
  {
    "id": 124,
    "Name_pt": "Radite",
    "Cod_Fresco": 2754,
    "Cod_Mix": null,
    "Categoria_Alimentos": "Hortaliças",
    "Inicial_Nome": "R"
  },
  {
    "id": 125,
    "Name_pt": "Repolho roxo",
    "Cod_Fresco": 2416,
    "Cod_Mix": 503,
    "Categoria_Alimentos": "Hortaliças",
    "Inicial_Nome": "R"
  },
  {
    "id": 126,
    "Name_pt": "Repolho verde",
    "Cod_Fresco": 23,
    "Cod_Mix": 504,
    "Categoria_Alimentos": "Hortaliças",
    "Inicial_Nome": "R"
  },
  {
    "id": 129,
    "Name_pt": "Rúcula",
    "Cod_Fresco": 56,
    "Cod_Mix": null,
    "Categoria_Alimentos": "Hortaliças",
    "Inicial_Nome": "R"
  },
  {
    "id": 128,
    "Name_pt": "Rúcula hidropônica",
    "Cod_Fresco": 5865,
    "Cod_Mix": null,
    "Categoria_Alimentos": "Hortaliças",
    "Inicial_Nome": "R"
  },
  {
    "id": 130,
    "Name_pt": "Salsão",
    "Cod_Fresco": 73,
    "Cod_Mix": null,
    "Categoria_Alimentos": "Hortaliças",
    "Inicial_Nome": "S"
  },
  {
    "id": 131,
    "Name_pt": "Salsinha",
    "Cod_Fresco": 68,
    "Cod_Mix": null,
    "Categoria_Alimentos": "Hortaliças",
    "Inicial_Nome": "S"
  },
  {
    "id": 132,
    "Name_pt": "Tangerina / Ponkan",
    "Cod_Fresco": 41,
    "Cod_Mix": 412,
    "Categoria_Alimentos": "Frutas",
    "Inicial_Nome": "T"
  },
  {
    "id": 133,
    "Name_pt": "Tomate cereja",
    "Cod_Fresco": 74,
    "Cod_Mix": 632,
    "Categoria_Alimentos": "Hortaliças",
    "Inicial_Nome": "T"
  },
  {
    "id": 134,
    "Name_pt": "Tomate longa vida",
    "Cod_Fresco": 18,
    "Cod_Mix": 355,
    "Categoria_Alimentos": "Hortaliças",
    "Inicial_Nome": "T"
  },
  {
    "id": 127,
    "Name_pt": "Tomate roma",
    "Cod_Fresco": 603,
    "Cod_Mix": 1295,
    "Categoria_Alimentos": "Hortaliças",
    "Inicial_Nome": "T"
  },
  {
    "id": 135,
    "Name_pt": "Tomate salatede",
    "Cod_Fresco": 7219,
    "Cod_Mix": 356,
    "Categoria_Alimentos": "Hortaliças",
    "Inicial_Nome": "T"
  },
  {
    "id": 136,
    "Name_pt": "Uva Benitaka",
    "Cod_Fresco": 2238,
    "Cod_Mix": 421,
    "Categoria_Alimentos": "Frutas",
    "Inicial_Nome": "U"
  },
  {
    "id": 137,
    "Name_pt": "Uva Crimson",
    "Cod_Fresco": 525,
    "Cod_Mix": 916,
    "Categoria_Alimentos": "Frutas",
    "Inicial_Nome": "U"
  },
  {
    "id": 138,
    "Name_pt": "Uva Itália",
    "Cod_Fresco": 75,
    "Cod_Mix": 422,
    "Categoria_Alimentos": "Frutas",
    "Inicial_Nome": "U"
  },
  {
    "id": 139,
    "Name_pt": "Uva Nubia",
    "Cod_Fresco": 4248,
    "Cod_Mix": 424,
    "Categoria_Alimentos": "Frutas",
    "Inicial_Nome": "U"
  },
  {
    "id": 140,
    "Name_pt": "Uva rosada",
    "Cod_Fresco": 784,
    "Cod_Mix": 423,
    "Categoria_Alimentos": "Frutas",
    "Inicial_Nome": "U"
  },
  {
    "id": 143,
    "Name_pt": "Uva Rubi",
    "Cod_Fresco": 529,
    "Cod_Mix": 426,
    "Categoria_Alimentos": "Frutas",
    "Inicial_Nome": "U"
  },
  {
    "id": 141,
    "Name_pt": "Uva Thompson",
    "Cod_Fresco": 1526,
    "Cod_Mix": 494,
    "Categoria_Alimentos": "Frutas",
    "Inicial_Nome": "U"
  },
  {
    "id": 142,
    "Name_pt": "Uva Vitória",
    "Cod_Fresco": 527,
    "Cod_Mix": 495,
    "Categoria_Alimentos": "Frutas",
    "Inicial_Nome": "U"
  },
  {
    "id": 144,
    "Name_pt": "Vagem bdj",
    "Cod_Fresco": 201,
    "Cod_Mix": 490,
    "Categoria_Alimentos": "Hortaliças",
    "Inicial_Nome": "V"
  },
  {
    "id": 145,
    "Name_pt": "Vagem kg",
    "Cod_Fresco": 37,
    "Cod_Mix": 858,
    "Categoria_Alimentos": "Hortaliças",
    "Inicial_Nome": "V"
  }
]
